odoo/addons/delivery_carrier_city/README.rst
odoo/addons/delivery_carrier_city/__init__.py
odoo/addons/delivery_carrier_city/__manifest__.py
odoo/addons/delivery_carrier_city/i18n/delivery_carrier_city.pot
odoo/addons/delivery_carrier_city/i18n/es.po
odoo/addons/delivery_carrier_city/i18n/it.po
odoo/addons/delivery_carrier_city/models/__init__.py
odoo/addons/delivery_carrier_city/models/delivery_carrier.py
odoo/addons/delivery_carrier_city/readme/CONTRIBUTORS.rst
odoo/addons/delivery_carrier_city/readme/DESCRIPTION.rst
odoo/addons/delivery_carrier_city/static/description/icon.png
odoo/addons/delivery_carrier_city/static/description/index.html
odoo/addons/delivery_carrier_city/tests/__init__.py
odoo/addons/delivery_carrier_city/tests/test_delivery_carrier_city.py
odoo/addons/delivery_carrier_city/views/delivery_carrier.xml
odoo14_addon_delivery_carrier_city-14.0.1.0.1.dev10.dist-info/METADATA
odoo14_addon_delivery_carrier_city-14.0.1.0.1.dev10.dist-info/WHEEL
odoo14_addon_delivery_carrier_city-14.0.1.0.1.dev10.dist-info/top_level.txt
odoo14_addon_delivery_carrier_city-14.0.1.0.1.dev10.dist-info/RECORD
